<?xml version="1.0" encoding="utf-8" ?>
<dwsync>
<file name="buddypress-rtl.css" server="bv.kingbee.ovh" local="131757857036191020" remote="131756411400000000" Dst="2" />
<file name="buddypress-rtl.min.css" server="bv.kingbee.ovh" local="131757857036320675" remote="131756411400000000" Dst="2" />
<file name="buddypress.css" server="bv.kingbee.ovh" local="131757857036889141" remote="131756411400000000" Dst="2" />
<file name="embeds-activity-rtl.css" server="bv.kingbee.ovh" local="131757857036939014" remote="131756411400000000" Dst="2" />
<file name="buddypress.min.css" server="bv.kingbee.ovh" local="131757857037088617" remote="131756411400000000" Dst="2" />
<file name="embeds-activity-rtl.min.css" server="bv.kingbee.ovh" local="131757857037387801" remote="131756411400000000" Dst="2" />
<file name="embeds-activity.css" server="bv.kingbee.ovh" local="131757857037517457" remote="131756411400000000" Dst="2" />
<file name="embeds-activity.min.css" server="bv.kingbee.ovh" local="131757857037647116" remote="131756411400000000" Dst="2" />
<file name="twentyeleven-rtl.css" server="bv.kingbee.ovh" local="131757857038335282" remote="131756411400000000" Dst="2" />
<file name="twentyeleven-rtl.min.css" server="bv.kingbee.ovh" local="131757857038375162" remote="131756411400000000" Dst="2" />
<file name="twentyeleven.css" server="bv.kingbee.ovh" local="131757857079026467" remote="131756411400000000" Dst="2" />
<file name="twentyeleven.min.css" server="bv.kingbee.ovh" local="131757857039043403" remote="131756411400000000" Dst="2" />
<file name="twentyeleven.scss" server="bv.kingbee.ovh" local="131757857039392445" remote="131756411400000000" Dst="2" />
<file name="twentyfifteen-rtl.css" server="bv.kingbee.ovh" local="131757857039462258" remote="131756411400000000" Dst="2" />
<file name="twentyfifteen-rtl.min.css" server="bv.kingbee.ovh" local="131757857040260143" remote="131756411400000000" Dst="2" />
<file name="twentyfifteen.css" server="bv.kingbee.ovh" local="131757857075904829" remote="131756411400000000" Dst="2" />
<file name="twentyfifteen.min.css" server="bv.kingbee.ovh" local="131757857041427010" remote="131756411400000000" Dst="2" />
<file name="twentyfifteen.scss" server="bv.kingbee.ovh" local="131757857042334592" remote="131756411400000000" Dst="2" />
<file name="twentyfourteen-rtl.css" server="bv.kingbee.ovh" local="131757857042414368" remote="131756411400000000" Dst="2" />
<file name="twentyfourteen.css" server="bv.kingbee.ovh" local="131757857075934750" remote="131756411400000000" Dst="2" />
<file name="twentyfourteen-rtl.min.css" server="bv.kingbee.ovh" local="131757857043202268" remote="131756411400000000" Dst="2" />
<file name="twentyfourteen.min.css" server="bv.kingbee.ovh" local="131757857044079910" remote="131756411400000000" Dst="2" />
<file name="twentyfourteen.scss" server="bv.kingbee.ovh" local="131757857044319281" remote="131756411400000000" Dst="2" />
<file name="twentyseventeen-rtl.css" server="bv.kingbee.ovh" local="131757857045266743" remote="131756411400000000" Dst="2" />
<file name="twentyseventeen-rtl.min.css" server="bv.kingbee.ovh" local="131757857045406635" remote="131756411400000000" Dst="2" />
<file name="twentyseventeen.min.css" server="bv.kingbee.ovh" local="131757857046284048" remote="131756411400000000" Dst="2" />
<file name="twentyseventeen.css" server="bv.kingbee.ovh" local="131757857078817036" remote="131756411400000000" Dst="2" />
<file name="twentysixteen-rtl.css" server="bv.kingbee.ovh" local="131757857047381106" remote="131756411400000000" Dst="2" />
<file name="twentyseventeen.scss" server="bv.kingbee.ovh" local="131757857047550635" remote="131756411400000000" Dst="2" />
<file name="twentysixteen-rtl.min.css" server="bv.kingbee.ovh" local="131757857047999441" remote="131756411400000000" Dst="2" />
<file name="twentysixteen.min.css" server="bv.kingbee.ovh" local="131757857048498119" remote="131756411400000000" Dst="2" />
<file name="twentysixteen.css" server="bv.kingbee.ovh" local="131757857078986583" remote="131756411400000000" Dst="2" />
<file name="twentyten-rtl.css" server="bv.kingbee.ovh" local="131757857050333201" remote="131756411400000000" Dst="2" />
<file name="twentysixteen.scss" server="bv.kingbee.ovh" local="131757857050532655" remote="131756411400000000" Dst="2" />
<file name="twentyten-rtl.min.css" server="bv.kingbee.ovh" local="131757857050821884" remote="131756411400000000" Dst="2" />
<file name="twentyten.min.css" server="bv.kingbee.ovh" local="131757857051210847" remote="131756411400000000" Dst="2" />
<file name="twentyten.css" server="bv.kingbee.ovh" local="131757857075765188" remote="131756411400000000" Dst="2" />
<file name="twentyten.scss" server="bv.kingbee.ovh" local="131757857051779320" remote="131756411400000000" Dst="2" />
<file name="twentythirteen-rtl.css" server="bv.kingbee.ovh" local="131757857051918968" remote="131756411400000000" Dst="2" />
<file name="twentythirteen-rtl.min.css" server="bv.kingbee.ovh" local="131757857052068560" remote="131756411400000000" Dst="2" />
<file name="twentythirteen.min.css" server="bv.kingbee.ovh" local="131757857052886370" remote="131756411400000000" Dst="2" />
<file name="twentythirteen.css" server="bv.kingbee.ovh" local="131757857079644816" remote="131756411400000000" Dst="2" />
<file name="twentytwelve-rtl.css" server="bv.kingbee.ovh" local="131757857053923589" remote="131756411400000000" Dst="2" />
<file name="twentythirteen.scss" server="bv.kingbee.ovh" local="131757857054093140" remote="131756411400000000" Dst="2" />
<file name="twentytwelve-rtl.min.css" server="bv.kingbee.ovh" local="131757857055090472" remote="131756411400000000" Dst="2" />
<file name="twentytwelve.min.css" server="bv.kingbee.ovh" local="131757857055728761" remote="131756411400000000" Dst="2" />
<file name="twentytwelve.css" server="bv.kingbee.ovh" local="131757857076114260" remote="131756411400000000" Dst="2" />
<file name="twentytwelve.scss" server="bv.kingbee.ovh" local="131757857056217451" remote="131756411400000000" Dst="2" />
</dwsync>