<?xml version="1.0" encoding="utf-8" ?>
<dwsync>
<file name="bp-loader.php" server="bv.kingbee.ovh" local="131757856928040200" remote="131756411400000000" Dst="2" />
<file name="class-buddypress.php" server="bv.kingbee.ovh" local="131757857279670158" remote="131756411400000000" Dst="2" />
<file name="buddypress.pot" server="bv.kingbee.ovh" local="131757857281195873" remote="131756411400000000" Dst="2" />
<file name="composer.json" server="bv.kingbee.ovh" local="131757857304343973" remote="131756411400000000" Dst="2" />
<file name="favicon.ico" server="bv.kingbee.ovh" local="131757857305012184" remote="131756411400000000" Dst="2" />
<file name="humans.txt" server="bv.kingbee.ovh" local="131757857305141847" remote="131756411400000000" Dst="2" />
<file name="license.txt" server="bv.kingbee.ovh" local="131757857306109267" remote="131756411400000000" Dst="2" />
<file name="readme.txt" server="bv.kingbee.ovh" local="131757857306238901" remote="131756411400000000" Dst="2" />
</dwsync>